dask_cuda/GIT_COMMIT
dask_cuda/VERSION
dask_cuda/__init__.py
dask_cuda/_compat.py
dask_cuda/_version.py
dask_cuda/cli.py
dask_cuda/cuda_worker.py
dask_cuda/device_host_file.py
dask_cuda/disk_io.py
dask_cuda/get_device_memory_objects.py
dask_cuda/initialize.py
dask_cuda/is_device_object.py
dask_cuda/is_spillable_object.py
dask_cuda/local_cuda_cluster.py
dask_cuda/plugins.py
dask_cuda/proxify_device_objects.py
dask_cuda/proxify_host_file.py
dask_cuda/proxy_object.py
dask_cuda/utils.py
dask_cuda/utils_test.py
dask_cuda/worker_common.py
dask_cuda/worker_spec.py
dask_cuda/benchmarks/__init__.py
dask_cuda/benchmarks/common.py
dask_cuda/benchmarks/local_cudf_groupby.py
dask_cuda/benchmarks/local_cudf_merge.py
dask_cuda/benchmarks/local_cudf_shuffle.py
dask_cuda/benchmarks/local_cupy.py
dask_cuda/benchmarks/local_cupy_map_overlap.py
dask_cuda/benchmarks/read_parquet.py
dask_cuda/benchmarks/utils.py
dask_cuda/explicit_comms/__init__.py
dask_cuda/explicit_comms/comms.py
dask_cuda/explicit_comms/dataframe/__init__.py
dask_cuda/explicit_comms/dataframe/shuffle.py
dask_cuda/tests/conftest.py
dask_cuda/tests/test_cudf_builtin_spilling.py
dask_cuda/tests/test_dask_cuda_worker.py
dask_cuda/tests/test_dask_setup.py
dask_cuda/tests/test_device_host_file.py
dask_cuda/tests/test_dgx.py
dask_cuda/tests/test_explicit_comms.py
dask_cuda/tests/test_from_array.py
dask_cuda/tests/test_gds.py
dask_cuda/tests/test_initialize.py
dask_cuda/tests/test_local_cuda_cluster.py
dask_cuda/tests/test_proxify_host_file.py
dask_cuda/tests/test_proxy.py
dask_cuda/tests/test_spill.py
dask_cuda/tests/test_utils.py
dask_cuda/tests/test_version.py
dask_cuda/tests/test_worker_spec.py
dask_cuda-25.12.0.dist-info/licenses/LICENSE
shared-actions/check_nightly_success/check-nightly-success/check.py
shared-actions/telemetry-impls/summarize/bump_time.py
shared-actions/telemetry-impls/summarize/send_trace.py
dask_cuda-25.12.0.dist-info/METADATA
dask_cuda-25.12.0.dist-info/WHEEL
dask_cuda-25.12.0.dist-info/entry_points.txt
dask_cuda-25.12.0.dist-info/top_level.txt
dask_cuda-25.12.0.dist-info/RECORD
