Metadata-Version: 2.4
Name: dask-cuda
Version: 25.12.0
Summary: Utilities for Dask and CUDA interactions
Author: NVIDIA Corporation
License: Apache-2.0
Project-URL: Homepage, https://github.com/rapidsai/dask-cuda
Project-URL: Documentation, https://docs.rapids.ai/api/dask-cuda/stable/
Project-URL: Source, https://github.com/rapidsai/dask-cuda
Classifier: Intended Audience :: Developers
Classifier: Topic :: Database
Classifier: Topic :: Scientific/Engineering
Classifier: License :: OSI Approved :: Apache Software License
Classifier: Programming Language :: Python :: 3
Classifier: Programming Language :: Python :: 3.10
Classifier: Programming Language :: Python :: 3.11
Classifier: Programming Language :: Python :: 3.12
Classifier: Programming Language :: Python :: 3.13
Requires-Python: >=3.10
License-File: LICENSE
Requires-Dist: click>=8.1
Requires-Dist: cuda-core==0.3.*
Requires-Dist: numba-cuda<0.20.0a0,>=0.19.1
Requires-Dist: numpy<3.0a0,>=1.23
Requires-Dist: nvidia-ml-py>=12
Requires-Dist: pandas>=1.3
Requires-Dist: rapids-dask-dependency==25.12.*
Requires-Dist: zict>=2.0.0
Provides-Extra: docs
Requires-Dist: numpydoc>=1.1.0; extra == "docs"
Requires-Dist: sphinx; extra == "docs"
Requires-Dist: sphinx-click>=2.7.1; extra == "docs"
Requires-Dist: sphinx-rtd-theme>=0.5.1; extra == "docs"
Provides-Extra: cu12
Requires-Dist: cuda-core[cu12]==0.3.*; extra == "cu12"
Requires-Dist: numba-cuda[cu12]<0.20.0a0,>=0.19.1; extra == "cu12"
Provides-Extra: cu13
Requires-Dist: cuda-core[cu13]==0.3.*; extra == "cu13"
Requires-Dist: numba-cuda[cu13]<0.20.0a0,>=0.19.1; extra == "cu13"
Dynamic: license-file
